omieapi/__init__.py
omieapi/omie.py
api_omie-0.2.5.dist-info/LICENCE
api_omie-0.2.5.dist-info/METADATA
api_omie-0.2.5.dist-info/WHEEL
api_omie-0.2.5.dist-info/top_level.txt
api_omie-0.2.5.dist-info/RECORD
