Metadata-Version: 2.1
Name: api-omie
Version: 0.2.5
Summary: Ferramenta para api do omie não oficial
Home-page: https://github.com/MikalROn/ApiOmie-nao-oficial
Author: Daniel Coêlho
Author-email: heromon.9010@gmail.com
License: MIT license
Project-URL: Demonstrações, https://github.com/MikalROn/ApiOmie-nao-oficial/tree/main/demos
Keywords: Api omie,omie,api do omie,omieapi
Requires-Python: >=3
License-File: LICENCE
Requires-Dist: requests
Requires-Dist: beautifulsoup4
